nala/__init__.py
nala/__main__.py
nala/api.py
nala/cli.py
nala/generator.py
nala/inspect.py
nala/real_variadic_functions.c
nala/rename_parameters.txt
nala/version.py
nala/wrap_internal_symbols.py
nala/dist/nala.c
nala/dist/nala.h
nala/subcommands/init/Makefile
nala/subcommands/init/test.mk
nala/subcommands/init/test_assertions.c
nala/subcommands/init/test_time.c
nala/templates/nala.c
nala/templates/nala_mocks.c.jinja2
nala/templates/nala_mocks.h.jinja2
nala-0.178.0.dist-info/LICENSE
nala-0.178.0.dist-info/METADATA
nala-0.178.0.dist-info/WHEEL
nala-0.178.0.dist-info/entry_points.txt
nala-0.178.0.dist-info/top_level.txt
nala-0.178.0.dist-info/RECORD
