Metadata-Version: 2.1
Name: nala
Version: 0.178.0
Summary: A test framework for C projects.
Home-page: https://github.com/eerimoq/nala
Author: Erik Moqvist and Valentin Berlier
Author-email: erik.moqvist@gmail.com
License: MIT
Keywords: c,test,mock
Platform: UNKNOWN
Classifier: License :: OSI Approved :: MIT License
Classifier: Programming Language :: Python :: 3
Requires-Dist: jinja2
Requires-Dist: pycparser (>=2.21)
